joulescope/stream_buffer.py
joulescope/datafile.py
joulescope/version.py
joulescope/parameters_v1.py
joulescope/view.py
joulescope/span.py
joulescope/parameter.py
joulescope/data_recorder.py
joulescope/__init__.py
joulescope/__main__.py
joulescope/jls_v2_writer.py
joulescope/time.py
joulescope/units.py
joulescope/file_replace.py
joulescope/entry_points/stream_test.py
joulescope/entry_points/program.py
joulescope/entry_points/capture.py
joulescope/entry_points/info.py
joulescope/entry_points/scan.py
joulescope/entry_points/statistics.py
joulescope/entry_points/bootloader_go.py
joulescope/entry_points/parameter_set.py
joulescope/entry_points/runner.py
joulescope/entry_points/__init__.py
joulescope/entry_points/gpo_demo.py
joulescope/entry_points/recording.py
joulescope/test/test_span.py
joulescope/test/test_data_recorder_downsampled.py
joulescope/test/test_time.py
joulescope/test/test_datafile.py
joulescope/test/test_jls_v2_writer.py
joulescope/test/test_data_recorder.py
joulescope/test/__init__.py
joulescope/test/test_file_replace.py
joulescope/test/test_units.py
joulescope/v1/js220.py
joulescope/v1/stream_buffer.py
joulescope/v1/device.py
joulescope/v1/js110.py
joulescope/v1/stats.c
joulescope/v1/__init__.py
joulescope/v1/sample_buffer.py
joulescope/v1/stats.cpython-311-x86_64-linux-gnu.so
joulescope/v1/driver.py
joulescope/v1/test/test_sample_buffer.py
joulescope/v1/test/__init__.py
joulescope/v0/filter_fir.c
joulescope/v0/notification_handler.py
joulescope/v0/array_storage.py
joulescope/v0/firmware_manager.py
joulescope/v0/bootloader.py
joulescope/v0/stream_buffer.c
joulescope/v0/filter_fir.cpython-311-x86_64-linux-gnu.so
joulescope/v0/decimators.py
joulescope/v0/pattern_buffer.c
joulescope/v0/public_keys.py
joulescope/v0/__init__.py
joulescope/v0/stream_buffer.cpython-311-x86_64-linux-gnu.so
joulescope/v0/pattern_buffer.cpython-311-x86_64-linux-gnu.so
joulescope/v0/driver.py
joulescope-1.3.1.dist-info/WHEEL
joulescope-1.3.1.dist-info/top_level.txt
joulescope-1.3.1.dist-info/entry_points.txt
joulescope-1.3.1.dist-info/RECORD
joulescope-1.3.1.dist-info/METADATA
joulescope-1.3.1.dist-info/licenses/LICENSE.txt
